cff2coins/CITATION.cff
cff2coins/__init__.py
cff2coins/main.py
cff2coins/models/__init__.py
cff2coins/models/cff_coin_span.py
cff2coins/models/cff_coin_span_json_decoder.py
cff2coins/models/cff_coin_span_json_encoder.py
cff2coins-1.0.0.dist-info/METADATA
cff2coins-1.0.0.dist-info/WHEEL
cff2coins-1.0.0.dist-info/licenses/LICENSE
cff2coins-1.0.0.dist-info/RECORD
