Metadata-Version: 2.4
Name: cff2coins
Version: 1.0.0
Summary: Creates COinS tags from CFF files. Can be used to help Zotero cite your software and datasets.
Project-URL: Homepage, https://github.com/willynilly/cff2coins
Project-URL: Documentation, https://github.com/willynilly/cff2coins#readme
Project-URL: Issues, https://github.com/willynilly/cff2coins/issues
Project-URL: Source, https://github.com/willynilly/cff2coins
Author-email: Will Riley <wanderingwill@gmail.com>
License-Expression: Apache-2.0
License-File: LICENSE
Keywords: CFF,COinS,Zotero,citation,metadata,parser
Classifier: Development Status :: 3 - Alpha
Classifier: Intended Audience :: Developers
Classifier: Intended Audience :: Education
Classifier: Intended Audience :: Information Technology
Classifier: Intended Audience :: Science/Research
Classifier: Intended Audience :: System Administrators
Classifier: License :: OSI Approved :: Apache Software License
Classifier: Natural Language :: English
Classifier: Programming Language :: Python
Classifier: Programming Language :: Python :: 3
Classifier: Programming Language :: Python :: 3.9
Classifier: Topic :: Scientific/Engineering
Classifier: Topic :: Software Development
Classifier: Topic :: Utilities
Requires-Python: >=3.9
Requires-Dist: coins-parser>=2.0.0
Requires-Dist: pyyaml>=6.0.2
Provides-Extra: testing
Requires-Dist: pytest>=8.3.5; extra == 'testing'
